LICENSE.md
MANIFEST.in
README.md
metadata.py
setup.py
django_uswds_forms.egg-info/PKG-INFO
django_uswds_forms.egg-info/SOURCES.txt
django_uswds_forms.egg-info/dependency_links.txt
django_uswds_forms.egg-info/not-zip-safe
django_uswds_forms.egg-info/requires.txt
django_uswds_forms.egg-info/top_level.txt
docs/Makefile
docs/conf.py
docs/developing.rst
docs/get_intersphinx_inventory.py
docs/index.rst
docs/introduction.rst
docs/make.bat
docs/quickstart.rst
docs/reference.rst
example/Procfile
example/db.sqlite3
example/manage.py
example/manifest.yml
example/requirements.txt
example/runtime.txt
example/app/__init__.py
example/app/example.py
example/app/jinja2.py
example/app/render_source.py
example/app/views.py
example/app/__pycache__/__init__.cpython-35.pyc
example/app/__pycache__/__init__.cpython-36.pyc
example/app/__pycache__/example.cpython-35.pyc
example/app/__pycache__/example.cpython-36.pyc
example/app/__pycache__/render_source.cpython-35.pyc
example/app/__pycache__/render_source.cpython-36.pyc
example/app/__pycache__/tests.cpython-35.pyc
example/app/__pycache__/tests.cpython-36.pyc
example/app/__pycache__/views.cpython-35.pyc
example/app/__pycache__/views.cpython-36.pyc
example/app/examples/__init__.py
example/app/examples/_startexample_template.py
example/app/examples/checkboxes.py
example/app/examples/date.py
example/app/examples/errors.py
example/app/examples/everything.py
example/app/examples/radios.py
example/app/examples/__pycache__/__init__.cpython-35.pyc
example/app/examples/__pycache__/__init__.cpython-36.pyc
example/app/examples/__pycache__/checkboxes.cpython-35.pyc
example/app/examples/__pycache__/checkboxes.cpython-36.pyc
example/app/examples/__pycache__/date.cpython-35.pyc
example/app/examples/__pycache__/date.cpython-36.pyc
example/app/examples/__pycache__/errors.cpython-35.pyc
example/app/examples/__pycache__/errors.cpython-36.pyc
example/app/examples/__pycache__/everything.cpython-35.pyc
example/app/examples/__pycache__/everything.cpython-36.pyc
example/app/examples/__pycache__/radios.cpython-35.pyc
example/app/examples/__pycache__/radios.cpython-36.pyc
example/app/jinja2/example_form_submission_alert.html
example/app/jinja2/examples/_startexample_template.html
